{
	"parent" : "minecraft:recipes/root",
  	"rewards" : {
    	"recipes" : [
      		"two:ruby_helmet"
    	]
  	},
  	"criteria" : {
    	"has_ruby" : {
      		"trigger" : "minecraft:inventory_changed",
      		"conditions" : {
        		"items" : [
          			{
            			"item" : "two:ruby"
          			}
        		]
      		}
    	},
    	"has_the_recipe" : {
      		"trigger" : "minecraft:recipe_unlocked",
      		"conditions" : {
        		"recipe" : "two:ruby_helmet"
      		}
    	}
  	},
  	"requirements" : [
    	[
      		"has_ruby",
      		"has_the_recipe"
    	]
  	]
}